cqdm_native.pypy38-pp73-x86_64-linux-gnu.so
cqdm/__init__.py
cqdm-1.0.5.dist-info/LICENCE
cqdm-1.0.5.dist-info/WHEEL
cqdm-1.0.5.dist-info/top_level.txt
cqdm-1.0.5.dist-info/RECORD
cqdm-1.0.5.dist-info/METADATA
